clive_log/__init__.py
clive_log/context.py
clive_log/fields.py
clive_log-0.0.1.dist-info/LICENSE
clive_log-0.0.1.dist-info/METADATA
clive_log-0.0.1.dist-info/WHEEL
clive_log-0.0.1.dist-info/top_level.txt
clive_log-0.0.1.dist-info/RECORD
