Metadata-Version: 2.1
Name: clive-log
Version: 0.0.1
Summary: A CLI live logging package
Home-page: https://github.com/heidtn/clive_log
Author: Nathan
Author-email: strigusconsilium@gmail.com
License: UNKNOWN
Platform: UNKNOWN
Classifier: Programming Language :: Python :: 3
Requires-Python: >=3.6
